DeepMIMOv3/__init__.py
DeepMIMOv3/ant_patterns.py
DeepMIMOv3/construct_deepmimo.py
DeepMIMOv3/consts.py
DeepMIMOv3/generator.py
DeepMIMOv3/params.py
DeepMIMOv3/raytracing_v2.py
DeepMIMOv3/raytracing_v3.py
DeepMIMOv3/sionna_adapter.py
DeepMIMOv3/utils.py
DeepMIMOv3/visualization.py
deepmimov3-0.2.9.dist-info/licenses/LICENSE.md
deepmimov3-0.2.9.dist-info/METADATA
deepmimov3-0.2.9.dist-info/WHEEL
deepmimov3-0.2.9.dist-info/top_level.txt
deepmimov3-0.2.9.dist-info/RECORD
