Metadata-Version: 2.4
Name: DeepMIMOv3
Version: 0.2.9
Summary: DeepMIMOv3
Home-page: https://deepmimo.net/
Author: Umut Demirhan, Ahmed Alkhateeb
Keywords: mmWave,MIMO,DeepMIMO,python,Beta
Classifier: Development Status :: 3 - Alpha
Classifier: Programming Language :: Python :: 3
Classifier: Operating System :: OS Independent
License-File: LICENSE.md
Requires-Dist: numpy
Requires-Dist: scipy
Requires-Dist: tqdm
Requires-Dist: matplotlib
Dynamic: author
Dynamic: classifier
Dynamic: description
Dynamic: description-content-type
Dynamic: home-page
Dynamic: keywords
Dynamic: license-file
Dynamic: requires-dist
Dynamic: summary
